aiowaqi/__init__.py
aiowaqi/const.py
aiowaqi/exceptions.py
aiowaqi/models.py
aiowaqi/py.typed
aiowaqi/util.py
aiowaqi/waqi.py
aiowaqi-3.0.1.dist-info/LICENSE.md
aiowaqi-3.0.1.dist-info/METADATA
aiowaqi-3.0.1.dist-info/WHEEL
aiowaqi-3.0.1.dist-info/RECORD
