Metadata-Version: 2.1
Name: aiowaqi
Version: 3.0.1
Summary: Asynchronous Python client for WAQI API.
Home-page: https://github.com/joostlek/python-waqi
License: MIT
Keywords: WAQI,api,async,client
Author: Joost Lekkerkerker
Author-email: joostlek@outlook.com
Maintainer: Joost Lekkerkerker
Maintainer-email: joostlek@outlook.com
Requires-Python: >=3.11,<4.0
Classifier: Development Status :: 5 - Production/Stable
Classifier: Framework :: AsyncIO
Classifier: Intended Audience :: Developers
Classifier: License :: OSI Approved :: MIT License
Classifier: Natural Language :: English
Classifier: Programming Language :: Python :: 3
Classifier: Programming Language :: Python :: 3.11
Classifier: Programming Language :: Python :: 3.12
Classifier: Topic :: Software Development :: Libraries :: Python Modules
Requires-Dist: aiohttp (>=3.0.0)
Requires-Dist: yarl (>=1.6.0)
Project-URL: Bug Tracker, https://github.com/joostlek/python-waqi/issues
Project-URL: Changelog, https://github.com/joostlek/python-waqi/releases
Project-URL: Documentation, https://github.com/joostlek/python-waqi
Project-URL: Repository, https://github.com/joostlek/python-waqi
